odoo/addons/announcement/README.rst
odoo/addons/announcement/__init__.py
odoo/addons/announcement/__manifest__.py
odoo/addons/announcement/demo/announcement_tag_demo.xml
odoo/addons/announcement/i18n/announcement.pot
odoo/addons/announcement/i18n/es.po
odoo/addons/announcement/i18n/it.po
odoo/addons/announcement/models/__init__.py
odoo/addons/announcement/models/announcement.py
odoo/addons/announcement/models/announcement_tag.py
odoo/addons/announcement/models/ir_http.py
odoo/addons/announcement/models/res_users.py
odoo/addons/announcement/readme/CONFIGURE.md
odoo/addons/announcement/readme/CONTRIBUTORS.md
odoo/addons/announcement/readme/DESCRIPTION.md
odoo/addons/announcement/readme/ROADMAP.md
odoo/addons/announcement/readme/USAGE.md
odoo/addons/announcement/security/announcement_security.xml
odoo/addons/announcement/security/ir.model.access.csv
odoo/addons/announcement/static/description/icon.png
odoo/addons/announcement/static/description/icon.svg
odoo/addons/announcement/static/description/index.html
odoo/addons/announcement/static/src/js/announcement_dialog/announcement_dialog.esm.js
odoo/addons/announcement/static/src/js/announcement_menu/announcement_menu.esm.js
odoo/addons/announcement/static/src/js/announcement_menu/announcement_menu.xml
odoo/addons/announcement/static/src/js/announcement_service/announcement_service.esm.js
odoo/addons/announcement/tests/__init__.py
odoo/addons/announcement/tests/test_announcement.py
odoo/addons/announcement/views/announcement_tag_views.xml
odoo/addons/announcement/views/announcement_views.xml
odoo/addons/announcement/wizards/__init__.py
odoo/addons/announcement/wizards/read_announcement_wizard.py
odoo/addons/announcement/wizards/read_announcement_wizard.xml
odoo_addon_announcement-18.0.1.0.1.dist-info/METADATA
odoo_addon_announcement-18.0.1.0.1.dist-info/WHEEL
odoo_addon_announcement-18.0.1.0.1.dist-info/top_level.txt
odoo_addon_announcement-18.0.1.0.1.dist-info/RECORD
