Metadata-Version: 2.1
Name: odoo-addon-announcement
Version: 18.0.1.0.1
Requires-Python: >=3.10
Requires-Dist: odoo==18.0.*
Summary: Notify internal users about relevant organization stuff
Home-page: https://github.com/OCA/server-ux
License: AGPL-3
Author: Tecnativa, Odoo Community Association (OCA)
Author-email: support@odoo-community.org
Classifier: Programming Language :: Python
Classifier: Framework :: Odoo
Classifier: Framework :: Odoo :: 18.0
Classifier: License :: OSI Approved :: GNU Affero General Public License v3
